BahnarTextAugmentation/EDA.py
BahnarTextAugmentation/MTLCombination.py
BahnarTextAugmentation/SentenceBoundary.py
BahnarTextAugmentation/Single.py
BahnarTextAugmentation/Word2Vec.py
BahnarTextAugmentation/__init__.py
BahnarTextAugmentation/_version.py
BahnarTextAugmentation/utils.py
BahnarTextAugmentation-1.0.3.dist-info/METADATA
BahnarTextAugmentation-1.0.3.dist-info/WHEEL
BahnarTextAugmentation-1.0.3.dist-info/top_level.txt
BahnarTextAugmentation-1.0.3.dist-info/RECORD
